AUTHORS.rst
CONTRIBUTING.rst
HISTORY.rst
LICENSE
MANIFEST.in
README.rst
requirements.txt
setup.cfg
setup.py
src/jukebox_core.egg-info/PKG-INFO
src/jukebox_core.egg-info/SOURCES.txt
src/jukebox_core.egg-info/dependency_links.txt
src/jukebox_core.egg-info/entry_points.txt
src/jukebox_core.egg-info/not-zip-safe
src/jukebox_core.egg-info/requires.txt
src/jukebox_core.egg-info/top_level.txt
src/jukeboxcore/__init__.py
src/jukeboxcore/action.py
src/jukeboxcore/constants.py
src/jukeboxcore/djadapter.py
src/jukeboxcore/djsettings.py
src/jukeboxcore/errors.py
src/jukeboxcore/filesys.py
src/jukeboxcore/iniconf.py
src/jukeboxcore/launcher.py
src/jukeboxcore/log.py
src/jukeboxcore/main.py
src/jukeboxcore/ostool.py
src/jukeboxcore/plugins.py
src/jukeboxcore/reftrack.py
src/jukeboxcore/release.py
src/jukeboxcore/signals.py
src/jukeboxcore/addons/__init__.py
src/jukeboxcore/addons/configer/__init__.py
src/jukeboxcore/addons/configer/configer.py
src/jukeboxcore/addons/configer/configer.ui
src/jukeboxcore/addons/configer/configer_ui.py
src/jukeboxcore/addons/genesis/__init__.py
src/jukeboxcore/addons/genesis/genesis.py
src/jukeboxcore/addons/genesis/genesis.ui
src/jukeboxcore/addons/genesis/genesis_ui.py
src/jukeboxcore/addons/guerilla/__init__.py
src/jukeboxcore/addons/guerilla/guerillamgmt.py
src/jukeboxcore/data/corespec.ini
src/jukeboxcore/data/icons/JB_Icon_32x32.png
src/jukeboxcore/data/icons/JB_Icon_500x500.png
src/jukeboxcore/data/icons/alien.png
src/jukeboxcore/data/icons/asset.png
src/jukeboxcore/data/icons/checkbox.png
src/jukeboxcore/data/icons/delete_border_24x24.png
src/jukeboxcore/data/icons/down_arrow.png
src/jukeboxcore/data/icons/duplicate_border_24x24.png
src/jukeboxcore/data/icons/glyphicons_003_user.png
src/jukeboxcore/data/icons/glyphicons_144_folder_open.png
src/jukeboxcore/data/icons/glyphicons_181_download_alt.png
src/jukeboxcore/data/icons/glyphicons_433_plus.png
src/jukeboxcore/data/icons/glyphicons_433_plus_bright.png
src/jukeboxcore/data/icons/glyphicons_446_floppy_save.png
src/jukeboxcore/data/icons/handle.png
src/jukeboxcore/data/icons/import_border_24x24.png
src/jukeboxcore/data/icons/imported.png
src/jukeboxcore/data/icons/load_border_24x24.png
src/jukeboxcore/data/icons/menu_border_24x24.png
