Metadata-Version: 1.1
Name: jukebox-core
Version: 3.3.0
Summary: Core package for the jukebox pipeline.
Home-page: https://github.com/JukeboxPipeline/jukebox-core
Author: David Zuber
Author-email: zuber.david@gmx.de
License: BSD
Keywords: jukebox-core
Platform: UNKNOWN
Classifier: Development Status :: 3 - Alpha
Classifier: Intended Audience :: Developers
Classifier: License :: OSI Approved :: BSD License
Classifier: Natural Language :: English
Classifier: Programming Language :: Python :: 2.7
